{
  "strategy_name": "XAUUSD_PriorDay_Breakout",
  "version": "v1.0_baseline",
  "start_date": "2018-01-04",
  "end_date": "2021-12-31",
  "total_trades": 550,
  "tp_count": 171,
  "sl_count": 265,
  "sl_gap_count": 87,
  "time_exit_count": 27,
  "end_of_data_count": 0,
  "win_count": 185,
  "loss_count": 365,
  "win_rate": 0.3364,
  "avg_win_r": 1.428,
  "avg_loss_r": -1.1797,
  "expectancy_r": -0.3026,
  "profit_factor": 0.6135,
  "median_r": -1.0,
  "best_trade_r": 1.5,
  "worst_trade_r": -11.6535,
  "long_summary": {
    "trade_count": 298,
    "win_count": 106,
    "win_rate": 0.3557,
    "expectancy_r": -0.2585,
    "avg_win_r": 1.407,
    "avg_loss_r": -1.178
  },
  "short_summary": {
    "trade_count": 252,
    "win_count": 79,
    "win_rate": 0.3135,
    "expectancy_r": -0.3547,
    "avg_win_r": 1.4562,
    "avg_loss_r": -1.1816
  },
  "net_pnl_usd": -82109.12,
  "initial_equity": 100000.0,
  "final_equity": 17890.88,
  "total_return_pct": -82.1091,
  "max_drawdown_pct": 0.8321,
  "sharpe_approx": -3.4422,
  "params_snapshot": {
    "candle_minutes": 15,
    "signal_window_utc": "07:00-20:00",
    "time_exit_utc_hour": 21,
    "min_pdr_pct": 0.003,
    "max_pdr_pct": 0.02,
    "spread_price": 0.3,
    "slippage_price": 0.2,
    "stop_buffer_floor_pct": 0.0003,
    "tp_r_multiplier": 1.5,
    "risk_pct": 0.01,
    "initial_equity": 100000.0
  },
  "passed_min_trade_count": true,
  "passed_oos_expectancy": null
}